crazy_vision/__init__.py
crazy_vision/frame_processor.py
crazy_vision/middleware.py
crazy_vision/model_inferance.py
crazy_vision/video_decoding.py
crazy_vision-0.1.0.dist-info/LICENSE
crazy_vision-0.1.0.dist-info/METADATA
crazy_vision-0.1.0.dist-info/WHEEL
crazy_vision-0.1.0.dist-info/top_level.txt
crazy_vision-0.1.0.dist-info/RECORD
