Metadata-Version: 2.1
Name: crazy-vision
Version: 0.1.0
Summary: A video decoding and model inference package using YOLO, OpenCV, and PyTorch
Home-page: https://github.com/yourusername/crazy-vision
Author: Your Name
Author-email: your.email@example.com
Classifier: Programming Language :: Python :: 3
Classifier: License :: OSI Approved :: MIT License
Classifier: Operating System :: OS Independent
Requires-Python: >=3.10
License-File: LICENSE
Requires-Dist: av
Requires-Dist: opencv-python
Requires-Dist: torch
Requires-Dist: numpy
Requires-Dist: requests
Requires-Dist: ultralytics
